jupywrapper/__init__.py
jupywrapper/jupywrapper.py
jupy_wrapper-0.0.2.dist-info/LICENSE
jupy_wrapper-0.0.2.dist-info/METADATA
jupy_wrapper-0.0.2.dist-info/WHEEL
jupy_wrapper-0.0.2.dist-info/top_level.txt
jupy_wrapper-0.0.2.dist-info/RECORD
